fetchers/__init__.py
fetchers/get_all_links.py
fetchers-0.1.0.dist-info/WHEEL
fetchers-0.1.0.dist-info/METADATA
fetchers-0.1.0.dist-info/RECORD
