Metadata-Version: 2.1
Name: fetchers
Version: 0.1.0
Summary: Website Scraper
License: MIT
Author: imjuanleonard
Author-email: julioanthonyleonard@gmail.com
Requires-Python: >=3.9,<4.0
Classifier: License :: OSI Approved :: MIT License
Classifier: Programming Language :: Python :: 3
Classifier: Programming Language :: Python :: 3.10
Classifier: Programming Language :: Python :: 3.9
Requires-Dist: beautifulsoup4 (>=4.10.0,<5.0.0)
Requires-Dist: requests (>=2.26.0,<3.0.0)
